Workbook
Name BasePrices: 'EX1'!$C$7:$D$17
Name Destination: 'EX1'!$K$6
Name Multipliers: 'EX1'!$F$7:$G$11
Name Type: 'EX1'!$K$7

Sheet vlookup
A1: CompleteID | B1: Date | C1: Region | D1: Employee | E1: Item | F1: Units | G1: Unit Cost | H1: Status
A2: 101 | B2: 39819 | C2: Quebec | D2: Jones | E2: Pencil | F2: 95 | G2: 1.99 | H2: Complete
A3: 102 | B3: 39853 | C3: Ontario | D3: Howard | E3: Pencil | F3: 36 | G3: 4.99 | H3: Complete
A4: 103 | B4: 39887 | C4: Alberta | D4: Sorvino | E4: Pencil | F4: 56 | G4: 2.99 | H4: Complete
A5: 104 | B5: 39904 | C5: Quebec | D5: Anderson | E5: Binder | F5: 60 | G5: 4.99 | H5: Complete
A6: 105 | B6: 39938 | C6: Ontario | D6: Howard | E6: Pencil | F6: 90 | G6: 4.99 | H6: Complete | L6: INQUIRY
A7: 106 | B7: 39955 | C7: Alberta | D7: Thompson | E7: Pencil | F7: 32 | G7: 1.99 | H7: In Progress | L7: ID | M7: Employee | N7: Units | O7: Status
A8: 107 | B8: 39972 | C8: Quebec | D8: Jones | E8: Binder | F8: 60 | G8: 8.99 | H8: In Progress | L8: 110 | N8: =VLOOKUP(L8,$A$2:$H$30,6,0) -> 35 | O8: =VLOOKUP(L8,$A$2:$H$30,8,0) -> On Hold
A9: 108 | B9: 39989 | C9: Ontario | D9: Morgan | E9: Pencil | F9: 90 | G9: 4.99 | H9: In Progress | L9: 111 | M9: =VLOOKUP(L9,$A$2:$H$30,4,0) -> Smith | N9: =VLOOKUP(L9,$A$2:$H$30,6,0) -> 2 | O9: =VLOOKUP(L9,$A$2:$H$30,8,0) -> In Progress
A10: 109 | B10: 40006 | C10: Quebec | D10: Howard | E10: Binder | F10: 29 | G10: 1.99 | H10: In Progress | L10: 101 | M10: =VLOOKUP(L10,$A$2:$H$30,4,0) -> Jones | N10: =VLOOKUP(L10,$A$2:$H$30,6,0) -> 95 | O10: =VLOOKUP(L10,$A$2:$H$30,8,0) -> Complete
A11: 110 | B11: 40040 | C11: Quebec | D11: Jones | E11: Pencil | F11: 35 | G11: 4.99 | H11: On Hold | L11: 119 | M11: =VLOOKUP(L11,$A$2:$H$30,4,0) -> Howard | N11: =VLOOKUP(L11,$A$2:$H$30,6,0) -> 96 | O11: =VLOOKUP(L11,$A$2:$H$30,8,0) -> On Hold
A12: 111 | B12: 40057 | C12: Ontario | D12: Smith | E12: Desk | F12: 2 | G12: 125 | H12: In Progress
A13: 112 | B13: 40074 | C13: Quebec | D13: Jones | E13: Pen Set | F13: 16 | G13: 15.99 | H13: Complete
A14: 113 | B14: 40091 | C14: Ontario | D14: Morgan | E14: Binder | F14: 28 | G14: 8.99 | H14: In Progress
A15: 114 | B15: 40108 | C15: Quebec | D15: Jones | E15: Pen | F15: 64 | G15: 8.99 | H15: In Progress
A16: 115 | B16: 40159 | C16: Ontario | D16: Smith | E16: Pencil | F16: 67 | G16: 1.29 | H16: In Progress
A17: 116 | B17: 40210 | C17: Ontario | D17: Smith | E17: Binder | F17: 87 | G17: 15 | H17: On Hold
A18: 117 | B18: 40244 | C18: Alberta | D18: Sorvino | E18: Binder | F18: 7 | G18: 19.99 | H18: In Progress
A19: 118 | B19: 40261 | C19: Ontario | D19: Howard | E19: Pen Set | F19: 50 | G19: 4.99 | H19: In Progress
A20: 119 | B20: 40295 | C20: Quebec | D20: Howard | E20: Pen | F20: 96 | G20: 4.99 | H20: On Hold
A21: 120 | B21: 40312 | C21: Ontario | D21: Gill | E21: Pencil | F21: 53 | G21: 1.29 | H21: In Progress
A22: 121 | B22: 40329 | C22: Ontario | D22: Gill | E22: Binder | F22: 80 | G22: 8.99 | H22: In Progress
A23: 122 | B23: 40380 | C23: Ontario | D23: Morgan | E23: Pen Set | F23: 55 | G23: 12.49 | H23: In Progress
... A30: 129 | B30: 40533 | C30: Ontario | D30: Gill | E30: Binder | F30: 28 | G30: 4.99 | H30: On Hold

Sheet hlookup
A1: CompleteID | B1: 101 | C1: 102 | D1: 103 | E1: 104 | F1: 105 | G1: 106 | H1: 107 | I1: 108 | J1: 109 | K1: 110 | L1: 111 | M1: 112 | N1: 113 | O1: 114 | P1: 115 | Q1: 116 | R1: 117 | S1: 118 | T1: 119 | U1: 120 | V1: 121 | W1: 122 | X1: 123 | Y1: 124 | Z1: 125 | AA1: 126 | AB1: 127 | AC1: 128 | AD1: 129
A2: Date | B2: 39819 | C2: 39853 | D2: 39887 | E2: 39904 | F2: 39938 | G2: 39955 | H2: 39972 | I2: 39989 | J2: 40006 | K2: 40040 | L2: 40057 | M2: 40074 | N2: 40091 | O2: 40108 | P2: 40159 | Q2: 40210 | R2: 40244 | S2: 40261 | T2: 40295 | U2: 40312 | V2: 40329 | W2: 40380 | X2: 40397 | Y2: 40414 | Z2: 40431 | AA2: 40448 | AB2: 40465 | AC2: 40482 | AD2: 40533
A3: Region | B3: Quebec | C3: Ontario | D3: Alberta | E3: Quebec | F3: Ontario | G3: Alberta | H3: Quebec | I3: Ontario | J3: Quebec | K3: Quebec | L3: Ontario | M3: Quebec | N3: Ontario | O3: Quebec | P3: Ontario | Q3: Ontario | R3: Alberta | S3: Ontario | T3: Quebec | U3: Ontario | V3: Ontario | W3: Ontario | X3: Ontario | Y3: Alberta | Z3: Ontario | AA3: Alberta | AB3: Alberta | AC3: Ontario | AD3: Ontario
A4: Employee | B4: Jones | C4: Howard | D4: Sorvino | E4: Anderson | F4: Howard | G4: Thompson | H4: Jones | I4: Morgan | J4: Howard | K4: Jones | L4: Smith | M4: Jones | N4: Morgan | O4: Jones | P4: Smith | Q4: Smith | R4: Sorvino | S4: Howard | T4: Howard | U4: Gill | V4: Gill | W4: Morgan | X4: Kivell | Y4: Sorvino | Z4: Gill | AA4: Sorvino | AB4: Thompson | AC4: Gill | AD4: Gill
A5: Item | B5: Pencil | C5: Pencil | D5: Pencil | E5: Binder | F5: Pencil | G5: Pencil | H5: Binder | I5: Pencil | J5: Binder | K5: Pencil | L5: Desk | M5: Pen Set | N5: Binder | O5: Pen | P5: Pencil | Q5: Binder | R5: Binder | S5: Pen Set | T5: Pen | U5: Pencil | V5: Binder | W5: Pen Set | X5: Pen Set | Y5: Desk | Z5: Pencil | AA5: Pen | AB5: Binder | AC5: Pencil | AD5: Binder
A6: Units | B6: 95 | C6: 36 | D6: 56 | E6: 60 | F6: 90 | G6: 32 | H6: 60 | I6: 90 | J6: 29 | K6: 35 | L6: 2 | M6: 16 | N6: 28 | O6: 64 | P6: 67 | Q6: 87 | R6: 7 | S6: 50 | T6: 96 | U6: 53 | V6: 80 | W6: 55 | X6: 42 | Y6: 3 | Z6: 7 | AA6: 76 | AB6: 57 | AC6: 14 | AD6: 28
A7: Unit Cost | B7: 1.99 | C7: 4.99 | D7: 2.99 | E7: 4.99 | F7: 4.99 | G7: 1.99 | H7: 8.99 | I7: 4.99 | J7: 1.99 | K7: 4.99 | L7: 125 | M7: 15.99 | N7: 8.99 | O7: 8.99 | P7: 1.29 | Q7: 15 | R7: 19.99 | S7: 4.99 | T7: 4.99 | U7: 1.29 | V7: 8.99 | W7: 12.49 | X7: 23.95 | Y7: 275 | Z7: 1.29 | AA7: 1.99 | AB7: 19.99 | AC7: 1.29 | AD7: 4.99
A8: Status | B8: Complete | C8: Complete | D8: Complete | E8: Complete | F8: Complete | G8: In Progress | H8: In Progress | I8: In Progress | J8: In Progress | K8: On Hold | L8: In Progress | M8: Complete | N8: In Progress | O8: In Progress | P8: In Progress | Q8: On Hold | R8: In Progress | S8: In Progress | T8: On Hold | U8: In Progress | V8: In Progress | W8: In Progress | X8: In Progress | Y8: In Progress | Z8: In Progress | AA8: In Progress | AB8: In Progress | AC8: In Progress | AD8: On Hold
E13: INQUIRY
E14: ID | F14: Date | G14: Item | H14: Status
E15: 111 | F15: =HLOOKUP(E15,$B$1:$AD$8,2,0) -> 40057 | G15: =HLOOKUP(E15,$B$1:$AD$8,5,0) -> Desk | H15: =HLOOKUP(E15,$B$1:$AD$8,8,0) -> In Progress
E16: 128 | F16: =HLOOKUP(E16,$B$1:$AD$8,2,0) -> 40482 | G16: =HLOOKUP(E16,$B$1:$AD$8,5,0) -> Pencil | H16: =HLOOKUP(E16,$B$1:$AD$8,8,0) -> In Progress
E17: 119 | F17: =HLOOKUP(E17,$B$1:$AD$8,2,0) -> 40295 | G17: =HLOOKUP(E17,$B$1:$AD$8,5,0) -> Pen | H17: =HLOOKUP(E17,$B$1:$AD$8,8,0) -> On Hold
E18: 129 | F18: =HLOOKUP(E18,$B$1:$AD$8,2,0) -> 40533 | G18: =HLOOKUP(E18,$B$1:$AD$8,5,0) -> Binder | H18: =HLOOKUP(E18,$B$1:$AD$8,8,0) -> On Hold

Sheet Invoice
B2: Invoice
B6: Invoice # | C6: 503254 | E6: Date | F6: =VLOOKUP(C6,_xlnm.Database,2,0) -> 41535
B8: Sales Rep | C8: =VLOOKUP(C6,_xlnm.Database,3,0) -> Morgan
B14: Cat | C14: Desc | D14: Unit Cost | E14: Units | F14: Total
B15: =VLOOKUP(C6,_xlnm.Database,4,0) -> Folders | C15: =VLOOKUP(C6,_xlnm.Database,5,0) -> Legal coloured | D15: =VLOOKUP(C6,_xlnm.Database,6,0) -> 2.59 | E15: =VLOOKUP(C6,_xlnm.Database,7,0) -> 17 | F15: =VLOOKUP(C6,_xlnm.Database,8,0) -> 44.03
D18: Tax | E18: 0.15 | F18: =F15*E18 -> 6.6045
D21: Total | F21: =F15+F18 -> 50.6345

Sheet EX1
C3: LOOKUP TABLES
C5: Base Prices | F5: Multipliers | J5: Enquiry System
C6: Destination | D6: Base Price | F6: Type | G6: % Multiplier | J6: Destination | K6: Barbados
C7: Barbados | D7: 532 | F7: Budget | G7: 1 | J7: Holiday Type | K7: Budget
C8: Florida | D8: 480 | F8: Standard | G8: 1.2 | J8: Base Price | K8: =VLOOKUP(Destination,BasePrices,2,0) -> 532
C9: Kenya | D9: 411 | F9: Luxury | G9: 1.5 | J9: Multiplier | K9: =VLOOKUP(Type,Multipliers,2,0) -> 1
C10: Paris | D10: 550 | F10: Opulent | G10: 2 | J10: Total | K10: =K8*K9 -> 532
C11: London | D11: 574 | F11: Hedonistic | G11: 3
C12: Tokyo | D12: 541
C13: Sydney | D13: 548
C14: Amsterdam | D14: 210
C15: Geneva | D15: 235
C16: Thailand | D16: 670
C17: Reykjavik | D17: 323

Sheet Data
A1: Invoice # | B1: Inv Date | C1: SalesRep | D1: Cat | E1: Desc | F1: Unit Cost | G1: Units | H1: Total
A2: 503241 | B2: 41518 | C2: Jardine | D2: Binder | E2: 1" reinforced | F2: 19.99 | G2: 47 | H2: =F2*G2 -> 939.53
A3: 503242 | B3: 41519 | C3: Brown | D3: Pens | E3: Gripper ball | F3: 1.29 | G3: 79 | H3: =F3*G3 -> 101.91
A4: 503243 | B4: 41520 | C4: Dunlop | D4: Pens | E4: Retractable | F4: 4.99 | G4: 20 | H4: =F4*G4 -> 99.8
A5: 503244 | B5: 41521 | C5: Aiello | D5: Binder | E5: 1" recycled | F5: 4.99 | G5: 100 | H5: =F5*G5 -> 499
A6: 503245 | B6: 41522 | C6: Parent | D6: Binder | E6: 2" high grade | F6: 8.99 | G6: 46 | H6: =F6*G6 -> 413.54
A7: 503246 | B7: 41523 | C7: Dunlop | D7: Office pads | E7: Memo tray refills | F7: 1.99 | G7: 52 | H7: =F7*G7 -> 103.48
A8: 503247 | B8: 41524 | C8: Jardine | D8: Clipboards | E8: Clear plastic | F8: 7.99 | G8: 63 | H8: =F8*G8 -> 503.37
A9: 503248 | B9: 41525 | C9: Gill | D9: Office pads | E9: Figuring pad insert | F9: 2.19 | G9: 76 | H9: =F9*G9 -> 166.44
A10: 503249 | B10: 41530 | C10: Kivell | D10: Clipboards | E10: Bear clip | F10: 6.99 | G10: 75 | H10: =F10*G10 -> 524.25
A11: 503250 | B11: 41531 | C11: Chan | D11: Clipboards | E11: Portfolio | F11: 3.99 | G11: 48 | H11: =F11*G11 -> 191.52
A12: 503251 | B12: 41532 | C12: Kivell | D12: Boxes | E12: Recycled storage | F12: 9.99 | G12: 17 | H12: =F12*G12 -> 169.83
A13: 503252 | B13: 41533 | C13: Brown | D13: Folders | E13: Hanging File frame | F13: 8.99 | G13: 86 | H13: =F13*G13 -> 773.14
... A25: 503264 | B25: 41525 | C25: Gill | D25: Office pads | E25: Figuring pad insert | F25: 2.19 | G25: 76 | H25: =F25*G25 -> 166.44

Sheet Vendor
B3: Vendor | C3: Jan | D3: Feb | E3: Mar | F3: Apr | G3: Total
B4: V101 | C4: =VLOOKUP(B4,'[1]North Section'!$A$5:$F$10,6,0) -> #N/A | D4: =VLOOKUP(B4,Feb!$C$4:$I$8,7,0) -> 14686.35 | E4: =VLOOKUP(B4,Mar!$C$4:$I$8,7,0) -> 20685 | F4: =VLOOKUP(B4,Apr!C4:I8,7,0) -> 5171.25 | G4: =SUM(C4:F4) -> #N/A
B5: V102 | C5: =VLOOKUP(B5,Jan!$C$4:$I$8,7,0) -> 34211 | D5: =VLOOKUP(B5,Feb!$C$4:$I$8,7,0) -> 72869.43 | E5: =VLOOKUP(B5,Mar!$C$4:$I$8,7,0) -> 102633 | F5: =VLOOKUP(B5,Apr!C5:I9,7,0) -> 25658.25 | G5: =SUM(C5:F5) -> 235371.68
B6: V103 | C6: =VLOOKUP(B6,Jan!$C$4:$I$8,7,0) -> 11941 | D6: =VLOOKUP(B6,Feb!$C$4:$I$8,7,0) -> 25434.33 | E6: =VLOOKUP(B6,Mar!$C$4:$I$8,7,0) -> 35823 | F6: =VLOOKUP(B6,Apr!C6:I10,7,0) -> 8955.75 | G6: =SUM(C6:F6) -> 82154.08
B7: V104 | C7: =VLOOKUP(B7,Jan!$C$4:$I$8,7,0) -> 22801 | D7: =VLOOKUP(B7,Feb!$C$4:$I$8,7,0) -> 48566.13 | E7: =VLOOKUP(B7,Mar!$C$4:$I$8,7,0) -> 68403 | F7: =VLOOKUP(B7,Apr!C7:I11,7,0) -> 17100.75 | G7: =SUM(C7:F7) -> 156870.88
B8: V105 | C8: =VLOOKUP(B8,Jan!$C$4:$I$8,7,0) -> 37569 | D8: =VLOOKUP(B8,Feb!$C$4:$I$8,7,0) -> 80021.97 | E8: =VLOOKUP(B8,Mar!$C$4:$I$8,7,0) -> 112707 | F8: =VLOOKUP(B8,Apr!C8:I12,7,0) -> 28176.75 | G8: =SUM(C8:F8) -> 258474.72
C13: Week1 | D13: Week2 | E13: Week3 | F13: Week4 | G13: Week5 | H13: Total
B14: Jan | C14: =HLOOKUP(C13,Jan!D3:I9,7,0) -> 22972 | D14: =HLOOKUP(D13,Jan!E3:J9,7,0) -> 27098 | E14: =HLOOKUP(E13,Jan!F3:K9,7,0) -> 23542 | F14: =HLOOKUP(F13,Jan!G3:L9,7,0) -> 20164 | G14: =HLOOKUP(G13,Jan!H3:M9,7,0) -> 19641 | H14: =HLOOKUP(H13,Jan!I3:N9,7,0) -> 113417
B15: Feb | C15: =HLOOKUP(C13,Feb!D3:I9,7,0) -> 62434.56 | D15: =HLOOKUP(D13,Feb!E3:J9,7,0) -> 57778.38 | E15: =HLOOKUP(E13,Feb!F3:K9,7,0) -> 47782.29 | F15: =HLOOKUP(F13,Feb!G3:L9,7,0) -> 36333.54 | G15: =HLOOKUP(G13,Feb!H3:M9,7,0) -> 37249.44 | H15: =HLOOKUP(H13,Feb!I3:N9,7,0) -> 241578.21
B16: Mar | C16: =HLOOKUP(C13,Mar!D3:I9,7,0) -> 87936 | D16: =HLOOKUP(D13,Mar!E3:J9,7,0) -> 81378 | E16: =HLOOKUP(E13,Mar!F3:K9,7,0) -> 67299 | F16: =HLOOKUP(F13,Mar!G3:L9,7,0) -> 51174 | G16: =HLOOKUP(G13,Mar!H3:M9,7,0) -> 52464 | H16: =HLOOKUP(H13,Mar!I3:N9,7,0) -> 340251
B17: Apr | C17: =HLOOKUP(C13,Apr!D3:I9,7,0) -> 21984 | D17: =HLOOKUP(D13,Apr!E3:J9,7,0) -> 20344.5 | E17: =HLOOKUP(E13,Apr!F3:K9,7,0) -> 16824.75 | F17: =HLOOKUP(F13,Apr!G3:L9,7,0) -> 12793.5 | G17: =HLOOKUP(G13,Apr!H3:M9,7,0) -> 13116 | H17: =HLOOKUP(H13,Apr!I3:N9,7,0) -> 85062.75

Sheet Jan
B3: Sno | C3: Vendor | D3: Week1 | E3: Week2 | F3: Week3 | G3: Week4 | H3: Week5 | I3: Total
B4: 1 | C4: V101 | D4: 3215 | E4: 1256 | F4: 1276 | G4: 534 | H4: 614 | I4: =SUM(D4:H4) -> 6895
B5: 2 | C5: V102 | D5: 8765 | E5: 9876 | F5: 6543 | G5: 4671 | H5: 4356 | I5: =SUM(D5:H5) -> 34211
B6: 3 | C6: V103 | D6: 1265 | E6: 3625 | F6: 2387 | G6: 2314 | H6: 2350 | I6: =SUM(D6:H6) -> 11941
B7: 4 | C7: V104 | D7: 2398 | E7: 4532 | F7: 5678 | G7: 4321 | H7: 5872 | I7: =SUM(D7:H7) -> 22801
B8: 5 | C8: V105 | D8: 7329 | E8: 7809 | F8: 7658 | G8: 8324 | H8: 6449 | I8: =SUM(D8:H8) -> 37569
C9: Total | D9: =SUM(D4:D8) -> 22972 | E9: =SUM(E4:E8) -> 27098 | F9: =SUM(F4:F8) -> 23542 | G9: =SUM(G4:G8) -> 20164 | H9: =SUM(H4:H8) -> 19641 | I9: =SUM(I4:I8) -> 113417

Sheet Feb
B3: Sno | C3: Vendor | D3: Week1 | E3: Week2 | F3: Week3 | G3: Week4 | H3: Week5 | I3: Total
B4: 1 | C4: V101 | D4: 2641.2 | E4: 6882.03 | F4: 2717.88 | G4: 1137.42 | H4: 1307.82 | I4: =SUM(D4:H4) -> 14686.35
B5: 2 | C5: V102 | D5: 26953.02 | E5: 21035.88 | F5: 11574.42 | G5: 8019.45 | H5: 5286.66 | I5: =SUM(D5:H5) -> 72869.43
B6: 3 | C6: V103 | D6: 6841.56 | E6: 3574.14 | F6: 5084.31 | G6: 4928.82 | H6: 5005.5 | I6: =SUM(D6:H6) -> 25434.33
B7: 4 | C7: V104 | D7: 5107.74 | E7: 9653.16 | F7: 12094.14 | G7: 9203.73 | H7: 12507.36 | I7: =SUM(D7:H7) -> 48566.13
B8: 5 | C8: V105 | D8: 20891.04 | E8: 16633.17 | F8: 16311.54 | G8: 13044.12 | H8: 13142.1 | I8: =SUM(D8:H8) -> 80021.97
C9: Total | D9: =SUM(D4:D8) -> 62434.56 | E9: =SUM(E4:E8) -> 57778.38 | F9: =SUM(F4:F8) -> 47782.29 | G9: =SUM(G4:G8) -> 36333.54 | H9: =SUM(H4:H8) -> 37249.44 | I9: =SUM(I4:I8) -> 241578.21

Sheet Mar
B3: Sno | C3: Vendor | D3: Week1 | E3: Week2 | F3: Week3 | G3: Week4 | H3: Week5 | I3: Total
B4: 1 | C4: V101 | D4: 3720 | E4: 9693 | F4: 3828 | G4: 1602 | H4: 1842 | I4: =SUM(D4:H4) -> 20685
B5: 2 | C5: V102 | D5: 37962 | E5: 29628 | F5: 16302 | G5: 11295 | H5: 7446 | I5: =SUM(D5:H5) -> 102633
B6: 3 | C6: V103 | D6: 9636 | E6: 5034 | F6: 7161 | G6: 6942 | H6: 7050 | I6: =SUM(D6:H6) -> 35823
B7: 4 | C7: V104 | D7: 7194 | E7: 13596 | F7: 17034 | G7: 12963 | H7: 17616 | I7: =SUM(D7:H7) -> 68403
B8: 5 | C8: V105 | D8: 29424 | E8: 23427 | F8: 22974 | G8: 18372 | H8: 18510 | I8: =SUM(D8:H8) -> 112707
C9: Total | D9: =SUM(D4:D8) -> 87936 | E9: =SUM(E4:E8) -> 81378 | F9: =SUM(F4:F8) -> 67299 | G9: =SUM(G4:G8) -> 51174 | H9: =SUM(H4:H8) -> 52464 | I9: =SUM(I4:I8) -> 340251

Sheet Apr
B3: Sno | C3: Vendor | D3: Week1 | E3: Week2 | F3: Week3 | G3: Week4 | H3: Week5 | I3: Total
B4: 1 | C4: V101 | D4: 930 | E4: 2423.25 | F4: 957 | G4: 400.5 | H4: 460.5 | I4: =SUM(D4:H4) -> 5171.25
B5: 2 | C5: V102 | D5: 9490.5 | E5: 7407 | F5: 4075.5 | G5: 2823.75 | H5: 1861.5 | I5: =SUM(D5:H5) -> 25658.25
B6: 3 | C6: V103 | D6: 2409 | E6: 1258.5 | F6: 1790.25 | G6: 1735.5 | H6: 1762.5 | I6: =SUM(D6:H6) -> 8955.75
B7: 4 | C7: V104 | D7: 1798.5 | E7: 3399 | F7: 4258.5 | G7: 3240.75 | H7: 4404 | I7: =SUM(D7:H7) -> 17100.75
B8: 5 | C8: V105 | D8: 7356 | E8: 5856.75 | F8: 5743.5 | G8: 4593 | H8: 4627.5 | I8: =SUM(D8:H8) -> 28176.75
C9: Total | D9: =SUM(D4:D8) -> 21984 | E9: =SUM(E4:E8) -> 20344.5 | F9: =SUM(F4:F8) -> 16824.75 | G9: =SUM(G4:G8) -> 12793.5 | H9: =SUM(H4:H8) -> 13116 | I9: =SUM(I4:I8) -> 85062.75

Sheet xlookup
B1: Date | C1: Region | D1: Employee | E1: CompleteID | F1: Item | G1: Units | H1: Unit Cost | I1: Status | K1: 109 | L1: =_xlfn.XLOOKUP(K1,E2:E30,D2:D30) -> Howard
B2: 39819 | C2: Quebec | D2: Jones | E2: 101 | F2: Pencil | G2: 95 | H2: 1.99 | I2: Complete
B3: 39853 | C3: Ontario | D3: Howard | E3: 102 | F3: Pencil | G3: 36 | H3: 4.99 | I3: Complete
B4: 39887 | C4: Alberta | D4: Sorvino | E4: 103 | F4: Pencil | G4: 56 | H4: 2.99 | I4: Complete
B5: 39904 | C5: Quebec | D5: Anderson | E5: 104 | F5: Binder | G5: 60 | H5: 4.99 | I5: Complete
B6: 39938 | C6: Ontario | D6: Howard | E6: 105 | F6: Pencil | G6: 90 | H6: 4.99 | I6: Complete
B7: 39955 | C7: Alberta | D7: Thompson | E7: 106 | F7: Pencil | G7: 32 | H7: 1.99 | I7: In Progress
B8: 39972 | C8: Quebec | D8: Jones | E8: 107 | F8: Binder | G8: 60 | H8: 8.99 | I8: In Progress
B9: 39989 | C9: Ontario | D9: Morgan | E9: 108 | F9: Pencil | G9: 90 | H9: 4.99 | I9: In Progress
B10: 40006 | C10: Quebec | D10: Howard | E10: 109 | F10: Binder | G10: 29 | H10: 1.99 | I10: In Progress
B11: 40040 | C11: Quebec | D11: Jones | E11: 110 | F11: Pencil | G11: 35 | H11: 4.99 | I11: On Hold
B12: 40057 | C12: Ontario | D12: Smith | E12: 111 | F12: Desk | G12: 2 | H12: 125 | I12: In Progress
B13: 40074 | C13: Quebec | D13: Jones | E13: 112 | F13: Pen Set | G13: 16 | H13: 15.99 | I13: Complete
... B30: 40533 | C30: Ontario | D30: Gill | E30: 129 | F30: Binder | G30: 28 | H30: 4.99 | I30: On Hold
